{
  "users": [
    {
      "id": 1,
      "name": "admin1",
      "email": "admin@gmail.com",
      "user_type": 1,
      "password": "admin",
      "user_last_connection": "",
      "registration_code": null,
      "active": 1,
      "udg_code": "u1920877",
      "createdAt": "0000-00-00 00:00:00",
      "updatedAt": "0000-00-00 00:00:00"
    },
    {
      "id": 2,
      "name": "Josep Planas Vendrell",
      "email": "profesor@gmail.com",
      "user_type": 2,
      "password": "profesor",
      "user_last_connection": "",
      "registration_code": null,
      "active": 1,
      "udg_code": "u1920877",
      "createdAt": "2018-02-01 00:00:00",
      "updatedAt": "2018-02-01 00:00:00"
    },
    {
      "id": 3,
      "name": "Carles Carlemany Terrats",
      "email": "profesor2@gmail.com",
      "user_type": 2,
      "password": "profesor",
      "user_last_connection": "",
      "registration_code": null,
      "active": 1,
      "udg_code": "u1920877",
      "createdAt": "2018-02-01 00:00:00",
      "updatedAt": "2018-02-01 00:00:00"
    },
    {
      "id": 8,
      "name": "Christian Gómez García",
      "email": "profesor3@gmail.com",
      "user_type": 2,
      "password": "profesor",
      "user_last_connection": "",
      "registration_code": null,
      "active": 1,
      "udg_code": "u1920877",
      "createdAt": "2018-02-01 00:00:00",
      "updatedAt": "2018-02-01 00:00:00"
    },
    {
      "id": 4,
      "name": "alumne1",
      "email": "alumne1@gmail.com",
      "user_type": 3,
      "password": "alumne",
      "user_last_connection": "",
      "registration_code": null,
      "active": 1,
      "udg_code": "u1914861",
      "createdAt": "2018-02-01 00:00:00",
      "updatedAt": "2018-02-01 00:00:00"
    },
    {
      "id": 5,
      "name": "alumne2",
      "email": "alumne2@gmail.com",
      "user_type": 3,
      "password": "alumne",
      "user_last_connection": "",
      "registration_code": null,
      "active": 1,
      "udg_code": "u1991291",
      "createdAt": "2018-02-01 00:00:00",
      "updatedAt": "2018-02-01 00:00:00"
    },
    {
      "id": 6,
      "name": "alumne3",
      "email": "alumne3@gmail.com",
      "user_type": 3,
      "password": "alumne",
      "user_last_connection": "",
      "registration_code": null,
      "active": 1,
      "udg_code": "u1975191",
      "createdAt": "2018-02-01 00:00:00",
      "updatedAt": "2018-02-01 00:00:00"
    },
    {
      "id": 7,
      "name": "alumne4",
      "email": "alumne4@gmail.com",
      "user_type": 3,
      "password": "alumne",
      "user_last_connection": "",
      "registration_code": null,
      "active": 1,
      "udg_code": "u1483191",
      "createdAt": "2018-02-01 00:00:00",
      "updatedAt": "2018-02-01 00:00:00"
    }
  ],
  "assignatures": [
    {
      "name": "Eng. software avançada",
      "code": 1,
      "credits":12,
      "id": 1
    },
    {
      "name": "CAES",
      "code": 1,
      "credits":15,
      "id": 2
    }
  ],
  "curs_user":[
    {
      "id":1,
      "curs_id":1,
      "usuari_id":4
    },
    {
      "id":2,
      "curs_id":2,
      "usuari_id":4
    },
    {
      "id":3,
      "curs_id":3,
      "usuari_id":4
    },
    {
      "id":4,
      "curs_id":4,
      "usuari_id":4
    }
  ],
  "curs_professor":[
    {
      "id":1,
      "curs_id":1,
      "usuari_id":2
    },
    {
      "id":2,
      "curs_id":1,
      "usuari_id":3
    },
    {
      "id":3,
      "curs_id":2,
      "usuari_id":2
    },
    {
      "id":4,
      "curs_id":2,
      "usuari_id":3
    },
    {
      "id":5,
      "curs_id":3,
      "usuari_id":8
    },
    {
      "id":6,
      "curs_id":4,
      "usuari_id":2
    }
  ],
  "cursos":[
    {
      "id":1,
      "assignatura_id":1,
      "data_inici":"25/01/2017",
      "data_fi":"30/06/2017",
      "maxim_alumnes_grup":4
    },
    {
      "id":2,
      "assignatura_id":1,
      "data_inici":"25/01/2018",
      "data_fi":"30/06/2018",
      "maxim_alumnes_grup":4
    },
    {
      "id":3,
      "assignatura_id":2,
      "data_inici":"25/01/2017",
      "data_fi":"30/06/2017",
      "maxim_alumnes_grup":6
    },
    {
      "id":4,
      "assignatura_id":2,
      "data_inici":"25/01/2018",
      "data_fi":"30/06/2018",
      "maxim_alumnes_grup":6
    }
  ],
  "sprints":[
    {
      "id":1,
      "numero_sprint":1,
      "cursId":1,
      "data_inici": "05/02/2018",
      "data_fi": "04/03/2018"
    },
    {
      "id":2,
      "numero_sprint":2,
      "cursId":1,
      "data_inici": "05/03/2018",
      "data_fi": "04/04/2018"
    },
    {
      "id":3,
      "numero_sprint":3,
      "cursId":1,
      "data_inici": "05/04/2018",
      "data_fi": "04/05/2018"
    },
    {
      "id":4,
      "numero_sprint":4,
      "cursId":1,
      "data_inici": "05/05/2018",
      "data_fi": "04/06/2018"
    }
  ],
  "grups":[
    {
      "id":1,
      "cursId":1,
      "nota_grup":null
    },
    {
      "id":2,
      "cursId":1,
      "nota_grup":null
    },
    {
      "id":3,
      "cursId":1,
      "nota_grup":null
    },
    {
      "id":4,
      "cursId":1,
      "nota_grup":null
    }
  ],
  "participacions":[
    {
      "id":1,
      "curs_id":1,
      "grup_id":1,
      "usuari_id":5,
      "nota_alumne":null,
      "percentatge_aportat":null,
      "actiu":1
    },
    {
      "id":2,
      "curs_id":1,
      "grup_id":1,
      "usuari_id":6,
      "nota_alumne":null,
      "percentatge_aportat":null,
      "actiu":1
    },
    {
      "id":3,
      "curs_id":1,
      "grup_id":1,
      "usuari_id":7,
      "nota_alumne":null,
      "percentatge_aportat":null,
      "actiu":1
    },
    {
      "id":4,
      "curs_id":1,
      "grup_id":1,
      "usuari_id":4,
      "nota_alumne":null,
      "percentatge_aportat":null,
      "actiu":1
    }
  ],
  "sprint_grups":[
    {
      "id": 1,
      "sprint_id":1,
      "grup_id":1,
      "numero_sprint":1,
      "data_inici": "05/02/2018",
      "data_fi": "04/03/2018",
      "estat":1
    },
    {
      "id": 1,
      "sprint_id":2,
      "grup_id":1,
      "numero_sprint":2,
      "data_inici": "05/03/2018",
      "data_fi": "04/04/2018",
      "estat":0
    },
    {
      "id": 1,
      "sprint_id":3,
      "grup_id":1,
      "numero_sprint":3,
      "data_inici": "05/04/2018",
      "data_fi": "04/05/2018",
      "estat":0
    },
    {
      "id": 1,
      "sprint_id":4,
      "grup_id":1,
      "numero_sprint":4,
      "data_inici": "05/05/2018",
      "data_fi": "04/06/2018",
      "estat":0
    }
  ],
  "histories":[
    {
      "id":1,
      "usuari_assignat":4,
      "sprint_group_id":1,
      "nom":"historia1",
      "descripcio":"Aquesta historia es una prova",
      "punts_historia":5,
      "estat":0
    },
    {
      "id":1,
      "usuari_assignat":null,
      "sprint_group_id":null,
      "nom":"historia2",
      "descripcio":"Aquesta historia 2 es una prova que forma part del backlog",
      "punts_historia":5,
      "estat":0
    }
  ],
  "tasques":[
    {
      "id":1,
      "usuari_assignat":4,
      "sprint_group_id":null,
      "historia_id":1,
      "nom":"tasca1",
      "descripcio":"Aquesta tasca assignada a la historia 1 es una prova",
      "estat":0
    },
    {
      "id":1,
      "usuari_assignat":4,
      "sprint_group_id":1,
      "historia_id":null,
      "nom":"tasca1",
      "descripcio":"Aquesta tasca assignada a la sprint1 es una prova",
      "estat":0
    },
    {
      "id":1,
      "usuari_assignat":4,
      "sprint_group_id":null,
      "historia_id":null,
      "nom":"tasca1",
      "descripcio":"Aquesta tasca es una prova que forma part del backlog",
      "estat":0
    }
  ],

  "acl":[
    {
      "component":"UsersPage",
      "type1":"1",
      "type2":"0",
      "type3":"0"
    },
    {
      "component":"ManageSubjectsPage",
      "type1":"1",
      "type2":"0",
      "type3":"0"
    },
    {
      "component":"ViewSubjectsPage",
      "type1":"0",
      "type2":"1",
      "type3":"0"
    }

  ],
  "images": [],
  "profile": {
    "name": "typicode"
  }
}